snopy/__init__.py
snopy/_elements/__init__.py
snopy/_elements/database.py
snopy/_elements/file_format.py
snopy/_elements/role.py
snopy/_elements/schema.py
snopy/_elements/snowflake_connector.py
snopy/_elements/stage.py
snopy/_elements/storage_integration.py
snopy/_elements/warehouse.py
snopy/connect.py
snopy-0.1.1.dist-info/LICENSE
snopy-0.1.1.dist-info/WHEEL
snopy-0.1.1.dist-info/METADATA
snopy-0.1.1.dist-info/RECORD
