Metadata-Version: 2.1
Name: snopy
Version: 0.1.1
Summary: Snowflake API connector for Python
License: Apache-2.0
Keywords: snowflake,connector
Author: Mateusz Polakowski
Author-email: mateusz.polakowski.ds@gmail.com
Requires-Python: >=3.8,<4.0
Classifier: License :: OSI Approved :: Apache Software License
Classifier: License :: OSI Approved :: MIT License
Classifier: Programming Language :: Python
Classifier: Programming Language :: Python :: 3
Classifier: Programming Language :: Python :: 3.10
Classifier: Programming Language :: Python :: 3.8
Classifier: Programming Language :: Python :: 3.9
Requires-Dist: pandas (>=1.4.4,<2.0.0)
Requires-Dist: snowflake-connector-python (>=2.7.12,<3.0.0)
